LICENSE
README.md
setup.cfg
setup.py
absu/__init__.py
absu/__main__.py
absu.egg-info/PKG-INFO
absu.egg-info/SOURCES.txt
absu.egg-info/dependency_links.txt
absu.egg-info/requires.txt
absu.egg-info/top_level.txt
absu/modules/__init__.py
absu/modules/azureblobconnector.py
absu/modules/azureconnector.py
absu/modules/credentials.py
absu/modules/parameterparser.py
absu/modules/templates/__init__.py
absu/modules/templates/storage.py