Metadata-Version: 2.1
Name: absu
Version: 1.1.0
Summary: This module helps updating a static website hosted by Azure Blob Storage.
Home-page: https://github.com/Quisl/absu
Author: Jonas C. Rabe aka Quisl
License-File: LICENSE
